nicetoolkit/__init__.py
nicetoolkit/awslog.py
nicetoolkit/xmlformatter.py
nice_tool_kit-2025.1.6.dist-info/METADATA
nice_tool_kit-2025.1.6.dist-info/WHEEL
nice_tool_kit-2025.1.6.dist-info/entry_points.txt
nice_tool_kit-2025.1.6.dist-info/top_level.txt
nice_tool_kit-2025.1.6.dist-info/RECORD
